reflex_ag_grid/__init__.py
reflex_ag_grid/ag_grid.py
reflex_ag_grid/datasource.py
reflex_ag_grid/handlers.py
reflex_ag_grid/wrapper.py
reflex_ag_grid-0.0.9.dist-info/METADATA
reflex_ag_grid-0.0.9.dist-info/WHEEL
reflex_ag_grid-0.0.9.dist-info/top_level.txt
reflex_ag_grid-0.0.9.dist-info/RECORD
