Metadata-Version: 2.1
Name: reflex-ag-grid
Version: 0.0.9
Summary: AGGrid wrapping for Reflex
Author-email: Reflex Team <team@reflex.dev>
License: Apache-2.0
Project-URL: homepage, https://ag-grid-demo.reflex.run/
Project-URL: source, https://github.com/reflex-dev/reflex-ag-grid
Keywords: reflex-ag-grid,ag-grid,reflex,reflex-custom-components,aggrid,dashboard
Classifier: Development Status :: 4 - Beta
Requires-Python: >=3.10
Requires-Dist: reflex>=0.6.3
Provides-Extra: dev
Requires-Dist: build; extra == "dev"
Requires-Dist: twine; extra == "dev"
